sphinxcontrib_hep_pdgref-0.1.5-py3.8-nspkg.pth
sphinxcontrib/hep/pdgref/__init__.py
sphinxcontrib/hep/pdgref/entry.py
sphinxcontrib/hep/pdgref/py.typed
sphinxcontrib/hep/pdgref/role.py
sphinxcontrib/hep/pdgref/url.py
sphinxcontrib_hep_pdgref-0.1.5.dist-info/LICENSE
sphinxcontrib_hep_pdgref-0.1.5.dist-info/METADATA
sphinxcontrib_hep_pdgref-0.1.5.dist-info/WHEEL
sphinxcontrib_hep_pdgref-0.1.5.dist-info/namespace_packages.txt
sphinxcontrib_hep_pdgref-0.1.5.dist-info/top_level.txt
sphinxcontrib_hep_pdgref-0.1.5.dist-info/RECORD
