Metadata-Version: 2.1
Name: sphinxcontrib-hep-pdgref
Version: 0.1.5
Summary: Sphinx role for linking to PDG reviews and listing
Home-page: UNKNOWN
Author: Common Partial Wave Analysis
Author-email: compwa-admin@ep1.rub.de
Maintainer-email: compwa-admin@ep1.rub.de
License: BSD 3-Clause License
Project-URL: Tracker, https://github.com/ComPWA/sphinxcontrib-hep-pdgref/issues
Project-URL: Changelog, https://github.com/ComPWA/sphinxcontrib-hep-pdgref/releases
Project-URL: Documentation, https://github.com/ComPWA/sphinxcontrib-hep-pdgref/blob/main/README.md
Project-URL: Source, https://github.com/ComPWA/sphinxcontrib-hep-pdgref
Keywords: particle data group,pdg,reference,sphinx
Platform: UNKNOWN
Classifier: Development Status :: 3 - Alpha
Classifier: Intended Audience :: Developers
Classifier: License :: OSI Approved :: BSD License
Classifier: Natural Language :: English
Classifier: Operating System :: OS Independent
Classifier: Programming Language :: Python
Classifier: Programming Language :: Python :: 3.6
Classifier: Programming Language :: Python :: 3.7
Classifier: Programming Language :: Python :: 3.8
Classifier: Programming Language :: Python :: 3.9
Classifier: Programming Language :: Python :: 3.10
Classifier: Programming Language :: Python :: 3.11
Classifier: Topic :: Documentation
Classifier: Topic :: Utilities
Classifier: Typing :: Typed
Requires-Python: >=3.6
Requires-Dist: attrs >=20.1.0
Requires-Dist: docutils
Requires-Dist: Sphinx
Provides-Extra: dev
Requires-Dist: pre-commit >=1.4.0 ; extra == 'dev'
Requires-Dist: black ; extra == 'dev'
Requires-Dist: mypy >=0.730 ; extra == 'dev'
Requires-Dist: types-docutils ; extra == 'dev'
Requires-Dist: types-setuptools ; extra == 'dev'
Requires-Dist: ruff ; extra == 'dev'
Requires-Dist: pyquery ; extra == 'dev'
Requires-Dist: pytest ; extra == 'dev'
Requires-Dist: pytest-cov ; extra == 'dev'
Requires-Dist: pytest-xdist ; extra == 'dev'
Requires-Dist: tox >=1.9 ; extra == 'dev'
Provides-Extra: format
Requires-Dist: black ; extra == 'format'
Provides-Extra: lint
Requires-Dist: mypy >=0.730 ; extra == 'lint'
Requires-Dist: types-docutils ; extra == 'lint'
Requires-Dist: types-setuptools ; extra == 'lint'
Requires-Dist: ruff ; extra == 'lint'
Provides-Extra: mypy
Requires-Dist: mypy >=0.730 ; extra == 'mypy'
Requires-Dist: types-docutils ; extra == 'mypy'
Requires-Dist: types-setuptools ; extra == 'mypy'
Provides-Extra: sty
Requires-Dist: pre-commit >=1.4.0 ; extra == 'sty'
Requires-Dist: black ; extra == 'sty'
Requires-Dist: mypy >=0.730 ; extra == 'sty'
Requires-Dist: types-docutils ; extra == 'sty'
Requires-Dist: types-setuptools ; extra == 'sty'
Requires-Dist: ruff ; extra == 'sty'
Requires-Dist: pyquery ; extra == 'sty'
Requires-Dist: pytest ; extra == 'sty'
Requires-Dist: pytest-cov ; extra == 'sty'
Requires-Dist: pytest-xdist ; extra == 'sty'
Provides-Extra: test
Requires-Dist: pyquery ; extra == 'test'
Requires-Dist: pytest ; extra == 'test'
Requires-Dist: pytest-cov ; extra == 'test'
Requires-Dist: pytest-xdist ; extra == 'test'
